envoy_data_plane/.gitkeep
envoy_data_plane/__init__.py
envoy_data_plane/envoy/__init__.py
envoy_data_plane/envoy/admin/__init__.py
envoy_data_plane/envoy/admin/v2alpha/__init__.py
envoy_data_plane/envoy/admin/v3/__init__.py
envoy_data_plane/envoy/annotations/__init__.py
envoy_data_plane/envoy/api/__init__.py
envoy_data_plane/envoy/api/v2/__init__.py
envoy_data_plane/envoy/api/v2/auth/__init__.py
envoy_data_plane/envoy/api/v2/cluster/__init__.py
envoy_data_plane/envoy/api/v2/core/__init__.py
envoy_data_plane/envoy/api/v2/endpoint/__init__.py
envoy_data_plane/envoy/api/v2/listener/__init__.py
envoy_data_plane/envoy/api/v2/ratelimit/__init__.py
envoy_data_plane/envoy/api/v2/route/__init__.py
envoy_data_plane/envoy/config/__init__.py
envoy_data_plane/envoy/config/accesslog/__init__.py
envoy_data_plane/envoy/config/accesslog/v2/__init__.py
envoy_data_plane/envoy/config/accesslog/v3/__init__.py
envoy_data_plane/envoy/config/bootstrap/__init__.py
envoy_data_plane/envoy/config/bootstrap/v2/__init__.py
envoy_data_plane/envoy/config/bootstrap/v3/__init__.py
envoy_data_plane/envoy/config/cluster/__init__.py
envoy_data_plane/envoy/config/cluster/aggregate/__init__.py
envoy_data_plane/envoy/config/cluster/aggregate/v2alpha/__init__.py
envoy_data_plane/envoy/config/cluster/dynamic_forward_proxy/__init__.py
envoy_data_plane/envoy/config/cluster/dynamic_forward_proxy/v2alpha/__init__.py
envoy_data_plane/envoy/config/cluster/redis/__init__.py
envoy_data_plane/envoy/config/cluster/v3/__init__.py
envoy_data_plane/envoy/config/common/__init__.py
envoy_data_plane/envoy/config/common/dynamic_forward_proxy/__init__.py
envoy_data_plane/envoy/config/common/dynamic_forward_proxy/v2alpha/__init__.py
envoy_data_plane/envoy/config/common/key_value/__init__.py
envoy_data_plane/envoy/config/common/key_value/v3/__init__.py
envoy_data_plane/envoy/config/common/matcher/__init__.py
envoy_data_plane/envoy/config/common/matcher/v3/__init__.py
envoy_data_plane-1.0.1.dist-info/LICENSE
envoy_data_plane-1.0.1.dist-info/METADATA
envoy_data_plane-1.0.1.dist-info/WHEEL
envoy_data_plane-1.0.1.dist-info/RECORD
