Metadata-Version: 2.3
Name: envoy_data_plane
Version: 1.0.1
Summary: Python dataclasses for the Envoy Data-Plane-API
License: MIT
Author: Vasili Syrakis
Author-email: cetanu@gmail.com
Requires-Python: >=3.11,<4.0
Classifier: License :: OSI Approved :: MIT License
Classifier: Programming Language :: Python :: 3
Classifier: Programming Language :: Python :: 3.11
Classifier: Programming Language :: Python :: 3.12
Classifier: Programming Language :: Python :: 3.13
Requires-Dist: betterproto2 (==0.2.3)
Requires-Dist: grpcio-tools (>=1.67,<2.0)
